AUTHORS.rst
cked/__init__.py
cked/default_settings.py
cked/elf/__init__.py
cked/elf/connector.py
cked/elf/const.py
cked/elf/utils.py
cked/fields.py
cked/static/cked/ckeditor/CHANGES.md
cked/static/cked/ckeditor/LICENSE.md
cked/static/cked/ckeditor/README.md
cked/static/cked/ckeditor/SECURITY.md
cked/static/cked/ckeditor/adapters/jquery.js
cked/static/cked/ckeditor/bender-runner.config.json
cked/static/cked/ckeditor/build-config.js
cked/static/cked/ckeditor/ckeditor.js
cked/static/cked/ckeditor/config.js
cked/static/cked/ckeditor/contents.css
cked/static/cked/ckeditor/lang/af.js
cked/static/cked/ckeditor/lang/ar.js
cked/static/cked/ckeditor/lang/az.js
cked/static/cked/ckeditor/lang/bg.js
cked/static/cked/ckeditor/lang/bn.js
cked/static/cked/ckeditor/lang/bs.js
cked/static/cked/ckeditor/lang/ca.js
cked/static/cked/ckeditor/lang/cs.js
cked/static/cked/ckeditor/lang/cy.js
cked/static/cked/ckeditor/lang/da.js
cked/static/cked/ckeditor/lang/de-ch.js
cked/static/cked/ckeditor/lang/de.js
cked/static/cked/ckeditor/lang/el.js
cked/static/cked/ckeditor/lang/en-au.js
cked/static/cked/ckeditor/lang/en-ca.js
cked/static/cked/ckeditor/lang/en-gb.js
cked/static/cked/ckeditor/lang/en.js
cked/static/cked/ckeditor/lang/eo.js
cked/static/cked/ckeditor/lang/es-mx.js
cked/static/cked/ckeditor/lang/es.js
cked/static/cked/ckeditor/lang/et.js
cked/static/cked/ckeditor/lang/eu.js
cked/static/cked/ckeditor/lang/fa.js
cked/static/cked/ckeditor/lang/fi.js
cked/static/cked/ckeditor/lang/fo.js
cked/static/cked/ckeditor/lang/fr-ca.js
cked/static/cked/ckeditor/lang/fr.js
cked/static/cked/ckeditor/lang/gl.js
cked/static/cked/ckeditor/lang/gu.js
cked/static/cked/ckeditor/lang/he.js
cked/static/cked/ckeditor/lang/hi.js
cked/static/cked/ckeditor/lang/hr.js
cked/static/cked/ckeditor/lang/hu.js
cked/static/cked/ckeditor/lang/id.js
cked/static/cked/ckeditor/lang/is.js
cked/static/cked/ckeditor/lang/it.js
cked/static/cked/ckeditor/lang/ja.js
cked/static/cked/ckeditor/lang/ka.js
django_cked-2.0.2.dist-info/LICENSE.rst
django_cked-2.0.2.dist-info/WHEEL
django_cked-2.0.2.dist-info/METADATA
django_cked-2.0.2.dist-info/RECORD
